{
    "weeks": [
      {
        "week": "Week 1",
        "links": [
          {
            "url": "./lesson1/holygrail.html",
            "title": "Holy Grail"
          },
          {
            "url": "https://codepen.io/BraxtonMedeiros/pen/MWPGmWx",
            "title": "Applied JavaScript"
          }
        ]
      },
      {
        "week": "Week 2",
        "links": [
          {
            "url": "./lesson2/design.html",
            "title": "Design Principles"
          },
          {
            "url": "https://codepen.io/BraxtonMedeiros/pen/XWxEVGr",
            "title": "Hamburger Menu"
          },
          {
            "url": "./lesson2/bom.html",
            "title": "BOM Activity"
          }
        ]
      },
      {
        "week": "Week 3",
        "links": [
          {
            "url": "./lesson3/images/landscape.webp",
            "title": "WebP Image File Format"
          },
          {
            "url": "./lesson3/responsive-images.html",
            "title": "Responsive Images - Srcset"
          },
          {
            "url": "./lesson3/lazyload.html",
            "title": "Lazy Loading"
          }
        ]
      },
      {
        "week": "Week 4",
        "links": [
          {
            "url": "https://codepen.io/BraxtonMedeiros/pen/KKrwaXo",
            "title": "CSS Pseudo-Classes"
          },
          {
            "url": "./lesson4/images/CCS-Combinators.png",
            "title": "CSS Combinators"
          },
          {
            "url": "./lesson4/tablebuild.html",
            "title": "HTML Tables"
          },
          {
            "url": "./lesson4/form-start/index.html",
            "title": "HTML Forms"
          }
        ]
      },
      {
        "week": "Week 5",
        "links": [
          {
            "url": "./lesson5/prophets.html",
            "title": "Fetch API"
          },
          {
            "url": "./lesson5/weather.html",
            "title": "Weather API"
          }
        ]
      },
      {
        "week": "Week 6",
        "links": [
          {
            "url": "#",
            "title": "No activity available"
          }
        ]
      }
    ]
  }
  